apm_agent_utils/__init__.py
apm_agent_utils/client.py
apm_agent_utils/instrumentation.py
apm_agent_utils/utils.py
apm_agent_utils-1.4.dist-info/LICENSE
apm_agent_utils-1.4.dist-info/WHEEL
apm_agent_utils-1.4.dist-info/METADATA
apm_agent_utils-1.4.dist-info/RECORD
