Metadata-Version: 2.1
Name: apm-agent-utils
Version: 1.4
Summary: This package can help you create Elastic APM instrumentations using regex
Home-page: https://github.com/vuonglv1612/apm-agent-utils
License: MIT
Keywords: apm,elastic,utils,apm-utils,agent
Author: vuonglv
Author-email: it.vuonglv@gmail.com
Requires-Python: >=2.7
Classifier: License :: OSI Approved :: MIT License
Classifier: Programming Language :: Python :: 2
Classifier: Programming Language :: Python :: 2.7
Classifier: Programming Language :: Python :: 3
Classifier: Programming Language :: Python :: 3.4
Classifier: Programming Language :: Python :: 3.5
Classifier: Programming Language :: Python :: 3.6
Classifier: Programming Language :: Python :: 3.7
Classifier: Programming Language :: Python :: 3.8
Classifier: Programming Language :: Python :: 3.9
Requires-Dist: elastic-apm (>=5.4.0,<7.0.0)
Requires-Dist: qualname (>=0.1.0,<0.2.0)
Project-URL: Repository, https://github.com/vuonglv1612/apm-agent-utils
